coinflip/__init__.py
coinflip/cli.py
coinflip_yesno-0.1.1.dist-info/METADATA
coinflip_yesno-0.1.1.dist-info/WHEEL
coinflip_yesno-0.1.1.dist-info/entry_points.txt
coinflip_yesno-0.1.1.dist-info/top_level.txt
coinflip_yesno-0.1.1.dist-info/RECORD
