Metadata-Version: 2.4
Name: coinflip-yesno
Version: 0.1.1
Summary: A minimal CLI tool that flips a coin and answers yes or no
Author: Johnny Graber
Requires-Python: >=3.9
